mysql_connection_helper-0.2.0.dist-info/licenses/LICENCE
mysql_connectivity/__init__.py
mysql_connectivity/mysql_helper.py
tests/__init__.py
tests/test_connection.py
mysql_connection_helper-0.2.0.dist-info/METADATA
mysql_connection_helper-0.2.0.dist-info/WHEEL
mysql_connection_helper-0.2.0.dist-info/top_level.txt
mysql_connection_helper-0.2.0.dist-info/RECORD
